odoo/addons/l10n_ir_base/README.rst
odoo/addons/l10n_ir_base/__init__.py
odoo/addons/l10n_ir_base/__manifest__.py
odoo/addons/l10n_ir_base/i18n/fa.po
odoo/addons/l10n_ir_base/i18n/l10n_ir_base.pot
odoo/addons/l10n_ir_base/models/__init__.py
odoo/addons/l10n_ir_base/models/account_journal_dashboard.py
odoo/addons/l10n_ir_base/models/base_model.py
odoo/addons/l10n_ir_base/models/user_extensions.py
odoo/addons/l10n_ir_base/readme/CONTRIBUTORS.rst
odoo/addons/l10n_ir_base/readme/DESCRIPTION.rst
odoo/addons/l10n_ir_base/readme/INSTALL.rst
odoo/addons/l10n_ir_base/readme/USAGE.rst
odoo/addons/l10n_ir_base/static/description/icon.png
odoo/addons/l10n_ir_base/static/description/index.html
odoo/addons/l10n_ir_base/views/partner_preferences.xml
odoo/addons/l10n_ir_base/views/user_preferences.xml
odoo14_addon_l10n_ir_base-14.0.3.0.1.dist-info/METADATA
odoo14_addon_l10n_ir_base-14.0.3.0.1.dist-info/WHEEL
odoo14_addon_l10n_ir_base-14.0.3.0.1.dist-info/top_level.txt
odoo14_addon_l10n_ir_base-14.0.3.0.1.dist-info/RECORD
